neverd/__init__.py
neverd/app.py
neverd/cli.py
neverd/constants.py
neverd/forms.py
neverd/generic_widgets.py
neverd/helpers.py
neverd/menus.py
neverd/objects.py
neverd/popups.py
neverd/utils.py
neverd/images/load_icon.gif
neverd-0.1.0.dist-info/LICENSE.md
neverd-0.1.0.dist-info/METADATA
neverd-0.1.0.dist-info/WHEEL
neverd-0.1.0.dist-info/entry_points.txt
neverd-0.1.0.dist-info/top_level.txt
neverd-0.1.0.dist-info/RECORD
