Metadata-Version: 2.1
Name: neverd
Version: 0.1.0
Summary: A 2D reverse engineering tool
Home-page: https://github.com/lpereira95/neverd
Author: L. F. Pereira
Author-email: luisfgpereira95@gmail.com
License: UNKNOWN
Project-URL: Homepage, https://github.com/lpereira95/neverd
Project-URL: Bug Tracker, https://github.com/lpereira95/neverd/issues
Keywords: gui,tkinter,reverse engineering,2D dialog,geometry
Platform: UNKNOWN
Classifier: Programming Language :: Python :: 3.6
Classifier: Programming Language :: Python :: 3.7
Classifier: Programming Language :: Python :: 3.8
Classifier: Programming Language :: Python :: 3.9
Classifier: Programming Language :: Python :: 3.10
Classifier: License :: OSI Approved :: MIT License
Requires-Python: >=3.6
License-File: LICENSE.md
Requires-Dist: click
Requires-Dist: pillow
Requires-Dist: numpy
